memiter/__init__.py
memiter/py.typed
memiter-0.2.0.dist-info/LICENSE
memiter-0.2.0.dist-info/METADATA
memiter-0.2.0.dist-info/WHEEL
memiter-0.2.0.dist-info/RECORD
