Metadata-Version: 2.1
Name: memiter
Version: 0.2.0
Summary: A generator that extends the functionality of a generator. simplifying pagination and data access.
Home-page: https://github.com/xpinked/memiter
Author: Udi Shalev
Author-email: azsd91@gmail.com
Requires-Python: >=3.8,<4.0
Classifier: Programming Language :: Python :: 3
Classifier: Programming Language :: Python :: 3.8
Classifier: Programming Language :: Python :: 3.9
Classifier: Programming Language :: Python :: 3.10
Classifier: Programming Language :: Python :: 3.11
Classifier: Programming Language :: Python :: 3.12
